CHANGES.txt
COPYRIGHT.txt
LICENSE.txt
README.txt
TODO.txt
demo.db
ez_setup.py
setup.cfg
setup.py
standalone.py
repoze/__init__.py
repoze.dbbrowser.egg-info/PKG-INFO
repoze.dbbrowser.egg-info/SOURCES.txt
repoze.dbbrowser.egg-info/dependency_links.txt
repoze.dbbrowser.egg-info/entry_points.txt
repoze.dbbrowser.egg-info/namespace_packages.txt
repoze.dbbrowser.egg-info/not-zip-safe
repoze.dbbrowser.egg-info/requires.txt
repoze.dbbrowser.egg-info/top_level.txt
repoze/dbbrowser/__init__.py
repoze/dbbrowser/configure.zcml
repoze/dbbrowser/dbbrowser.py
repoze/dbbrowser/tests.py
repoze/dbbrowser/views.py
repoze/dbbrowser/static/css/dbbrowser.css
repoze/dbbrowser/static/css/ellipsis-xbl.xml
repoze/dbbrowser/static/css/ui.jqgrid.css
repoze/dbbrowser/static/css/ui-lightness/jquery-ui-1.7.2.custom.css
repoze/dbbrowser/static/css/ui-lightness/images/ui-bg_diagonals-thick_18_b81900_40x40.png
repoze/dbbrowser/static/css/ui-lightness/images/ui-bg_diagonals-thick_20_666666_40x40.png
repoze/dbbrowser/static/css/ui-lightness/images/ui-bg_flat_10_000000_40x100.png
repoze/dbbrowser/static/css/ui-lightness/images/ui-bg_glass_100_f6f6f6_1x400.png
repoze/dbbrowser/static/css/ui-lightness/images/ui-bg_glass_100_fdf5ce_1x400.png
repoze/dbbrowser/static/css/ui-lightness/images/ui-bg_glass_65_ffffff_1x400.png
repoze/dbbrowser/static/css/ui-lightness/images/ui-bg_gloss-wave_35_f6a828_500x100.png
repoze/dbbrowser/static/css/ui-lightness/images/ui-bg_highlight-soft_100_eeeeee_1x100.png
repoze/dbbrowser/static/css/ui-lightness/images/ui-bg_highlight-soft_75_ffe45c_1x100.png
repoze/dbbrowser/static/css/ui-lightness/images/ui-icons_222222_256x240.png
repoze/dbbrowser/static/css/ui-lightness/images/ui-icons_228ef1_256x240.png
repoze/dbbrowser/static/css/ui-lightness/images/ui-icons_ef8c08_256x240.png
repoze/dbbrowser/static/css/ui-lightness/images/ui-icons_ffd27a_256x240.png
repoze/dbbrowser/static/css/ui-lightness/images/ui-icons_ffffff_256x240.png
repoze/dbbrowser/static/js/Changes.txt
repoze/dbbrowser/static/js/index.html
repoze/dbbrowser/static/js/install.txt
repoze/dbbrowser/static/js/jquery-1.3.2.min.js
repoze/dbbrowser/static/js/jquery-ui-1.7.2.custom.min.js
repoze/dbbrowser/static/js/jquery.jqGrid.min.js
repoze/dbbrowser/static/js/css/ui-lightness/jquery-ui-1.7.2.custom.css
